subgram/__init__.py
subgram/client.py
subgram/constants.py
subgram/schemas.py
subgram-0.0.4.dist-info/METADATA
subgram-0.0.4.dist-info/WHEEL
subgram-0.0.4.dist-info/licenses/LICENSE
subgram-0.0.4.dist-info/RECORD
